{"cameraMode":{"drawMode":0,"name":"Shaded","section":"Shading Mode"},"sceneLighting":true,"audioPlay":false,"sceneViewState":{"m_AlwaysRefresh":false,"showFog":true,"showSkybox":true,"showFlares":true,"showImageEffects":true,"showParticleSystems":true,"showVisualEffectGraphs":true,"m_FxEnabled":true},"in2DMode":false,"pivot":{"x":-0.31593605875968935,"y":5.611324310302734,"z":11.389042854309082},"rotation":{"x":-0.12075641006231308,"y":0.5095189809799194,"z":-0.07248299568891525,"w":-0.8488562107086182},"size":10.0,"orthographic":false}